pipeiq_framework/__init__.py
pipeiq_framework/persona_client/persona_service.py
pipeiq_framework/phantom_client/errors.py
pipeiq_framework/phantom_client/phantom_wallet.py
pipeiq_framework/prime_intellect_client/__init__.py
pipeiq_framework/prime_intellect_client/client.py
pipeiq_framework/prime_intellect_client/exceptions.py
pipeiq_framework/prime_intellect_client/models.py
pipeiq_framework/solana_client/solana_wallet.py
pipeiq_framework/worldcoin_client/worldcoin.py
pipeiq-0.1.3.dist-info/METADATA
pipeiq-0.1.3.dist-info/WHEEL
pipeiq-0.1.3.dist-info/RECORD
