Metadata-Version: 2.3
Name: pipeiq
Version: 0.1.3
Summary: PIPEIQ is an open-source framework that enables developers to seamlessly connect and orchestrate AI tools across the Web2 and Web3 ecosystems. It abstracts away the complexities of identity, messaging, and orchestration by providing standardized primitives for agent coordination, tool invocation, and cross-network integration.
License: MIT
Author: Shankar R
Author-email: shankar@pipeiq.ai
Requires-Python: >=3.11,<4.0
Classifier: License :: OSI Approved :: MIT License
Classifier: Programming Language :: Python :: 3
Classifier: Programming Language :: Python :: 3.11
Classifier: Programming Language :: Python :: 3.12
Classifier: Programming Language :: Python :: 3.13
Requires-Dist: aiohttp (>=3.12.13)
Requires-Dist: base58 (>=2.1.1,<3.0.0)
Requires-Dist: ratelimit (>=2.2.1,<3.0.0)
Requires-Dist: requests (>=2.32.4)
Requires-Dist: solana (>=0.36.7,<0.37.0)
Project-URL: Repository, https://github.com/PIpeIQ/pipeiq-framework
